gdmty_django_recaptcha_enterprise/__init__.py
gdmty_django_recaptcha_enterprise/admin.py
gdmty_django_recaptcha_enterprise/apps.py
gdmty_django_recaptcha_enterprise/models.py
gdmty_django_recaptcha_enterprise/recaptcha.py
gdmty_django_recaptcha_enterprise/tests.py
gdmty_django_recaptcha_enterprise/utils.py
gdmty_django_recaptcha_enterprise/views.py
gdmty_django_recaptcha_enterprise/migrations/__init__.py
gdmty_django_recaptcha_enterprise-2023.12.post0.dist-info/LICENSE
gdmty_django_recaptcha_enterprise-2023.12.post0.dist-info/METADATA
gdmty_django_recaptcha_enterprise-2023.12.post0.dist-info/WHEEL
gdmty_django_recaptcha_enterprise-2023.12.post0.dist-info/top_level.txt
gdmty_django_recaptcha_enterprise-2023.12.post0.dist-info/RECORD
