Metadata-Version: 2.1
Name: gdmty-django-recaptcha-enterprise
Version: 2023.12.post0
Summary: Library for Django that implements Google's reCaptcha Enterprise
Author-email: César Benjamín <mathereall@gmail.com>
License: Apache License
Project-URL: Homepage, https://github.com/SIGAMty/gdmty-django-recaptcha-enterprise
Keywords: django,recaptcha,enterprise,google,captcha,recaptcha-enterprise
Classifier: License :: OSI Approved :: Apache Software License
Classifier: Programming Language :: Python
Classifier: Programming Language :: Python :: 3
Classifier: Programming Language :: Python :: 3.10
Classifier: Programming Language :: Python :: 3.11
Classifier: Framework :: Django
Classifier: Framework :: Django :: 4.2
Requires-Python: >=3.10
License-File: LICENSE
Requires-Dist: django >=4.2
Requires-Dist: google-cloud-recaptcha-enterprise
Requires-Dist: tomli ; python_version < "3.11"
Provides-Extra: dev
Requires-Dist: black ; extra == 'dev'
Requires-Dist: bumpver ; extra == 'dev'
Requires-Dist: isort ; extra == 'dev'
Requires-Dist: pip-tools ; extra == 'dev'
Requires-Dist: pytest ; extra == 'dev'
